fwdpy11-0.24.5.dist-info/RECORD
fwdpy11-0.24.5.dist-info/WHEEL
fwdpy11-0.24.5.dist-info/entry_points.txt
fwdpy11-0.24.5.dist-info/METADATA
fwdpy11-0.24.5.dist-info/licenses/COPYING
fwdpy11/_dev.py
fwdpy11/mutation_dominance.py
fwdpy11/_version.py
fwdpy11/regions.py
fwdpy11/__init__.py
fwdpy11/genetic_values.py
fwdpy11/libfwdpy11core.dylib
fwdpy11/discrete_demography.py
fwdpy11/custom_genetic_value_decorators.py
fwdpy11/_fwdpy11.cpython-313-darwin.so
fwdpy11/genetic_map_unit.py
fwdpy11/class_decorators.py
fwdpy11/__main__.py
fwdpy11/_evolvets.py
fwdpy11/tskit_tools/metadata_schema.py
fwdpy11/tskit_tools/_flags.py
fwdpy11/tskit_tools/metadata.py
fwdpy11/tskit_tools/__init__.py
fwdpy11/tskit_tools/_dump_tables_to_tskit.py
fwdpy11/_functions/data_matrix_from_tables.py
fwdpy11/_functions/__init__.py
fwdpy11/_functions/import_demes.py
fwdpy11/_functions/simplify_tables.py
fwdpy11/_types/model_params.py
fwdpy11/_types/variant_iterator.py
fwdpy11/_types/data_matrix_iterator.py
fwdpy11/_types/population_mixin.py
fwdpy11/_types/demography_debugger.py
fwdpy11/_types/diploid_population.py
fwdpy11/_types/demographic_model_details.py
fwdpy11/_types/new_mutation_data.py
fwdpy11/_types/tree_iterator.py
fwdpy11/_types/__init__.py
fwdpy11/_types/forward_demes_graph.py
fwdpy11/_types/demographic_model_citation.py
fwdpy11/_types/table_collection.py
fwdpy11/_types/data_matrix.py
fwdpy11/.dylibs/libgsl.25.dylib
fwdpy11/.dylibs/libgslcblas.0.dylib
fwdpy11/headers/fwdpp/install-sh
fwdpy11/headers/fwdpp/configure.ac
fwdpy11/headers/fwdpp/INSTALL
fwdpy11/headers/fwdpp/LICENSE
fwdpy11/headers/fwdpp/ChangeLog
fwdpy11/headers/fwdpp/AUTHORS
fwdpy11/headers/fwdpp/config.guess
fwdpy11/headers/fwdpp/depcomp
fwdpy11/headers/fwdpp/missing
fwdpy11/headers/fwdpp/.gitmodules
fwdpy11/headers/fwdpp/TODO
fwdpy11/headers/fwdpp/Makefile.am
fwdpy11/headers/fwdpp/README.md
fwdpy11/headers/fwdpp/pandoc.css
fwdpy11/headers/fwdpp/config.sub
fwdpy11/headers/fwdpp/COPYING
fwdpy11/headers/fwdpp/compile
fwdpy11/headers/fwdpp/NEWS
fwdpy11/headers/fwdpp/.gitignore
fwdpy11/headers/fwdpp/index.md
fwdpy11/headers/fwdpp/fwdpp.spec.in
