Metadata-Version: 2.2
Name: fwdpy11
Version: 0.24.5
Summary: Forward-time population genetic simulation in Python
Author-Email: "Kevin R. Thornton" <krthornt@uci.edu>
License: GNU GPL3+
Classifier: Intended Audience :: Science/Research
Classifier: Topic :: Scientific/Engineering :: Bio-Informatics
Classifier: License :: OSI Approved :: GNU General Public License v3 or later (GPLv3+)
Project-URL: Repository, https://github.com/molpopgen/fwdpy11
Project-URL: Issues, https://github.com/molpopgen/fwdpy11/issues
Project-URL: Documentation, https://molpopgen.github.io/fwdpy11
Requires-Python: <3.14,>=3.10
Requires-Dist: attrs>=20.3.0
Requires-Dist: numpy>=1.23.5
Requires-Dist: tskit>=0.5.6
Requires-Dist: demes~=0.2.2
Requires-Dist: Deprecated
